{ "compressionlevel":-1,
 "height":23,
 "infinite":false,
 "layers":[
        {
         "data":[4, 4, 4, 4, 4, 4, 4, 4, 4, 4, 4, 4, 4, 4, 4, 4, 4, 4, 4, 4, 4, 1, 1, 1, 1, 1, 1, 1, 1, 4, 4, 1, 1, 1, 1, 1, 1, 1, 1, 4, 4, 1, 4, 4, 1, 4, 4, 4, 1, 4, 4, 1, 4, 4, 4, 1, 4, 4, 1, 4, 4, 1, 4, 4, 1, 4, 4, 4, 1, 4, 4, 1, 4, 4, 4, 1, 4, 4, 1, 4, 4, 1, 1, 1, 1, 1, 1, 1, 1, 1, 1, 1, 1, 1, 1, 1, 1, 1, 1, 4, 4, 1, 4, 4, 1, 4, 1, 4, 4, 4, 4, 4, 4, 1, 4, 1, 4, 4, 1, 4, 4, 1, 1, 1, 1, 4, 1, 1, 1, 4, 4, 1, 1, 1, 4, 1, 1, 1, 1, 4, 4, 4, 4, 4, 1, 4, 4, 4, 1, 4, 4, 1, 4, 4, 4, 1, 4, 4, 4, 4, 4, 1, 1, 4, 1, 4, 1, 1, 1, 1, 1, 1, 1, 1, 4, 1, 4, 1, 1, 4, 4, 4, 4, 4, 1, 4, 1, 4, 4, 3, 3, 4, 4, 1, 4, 1, 4, 4, 4, 4, 4, 1, 1, 1, 1, 1, 1, 4, 1, 1, 1, 1, 4, 1, 1, 1, 1, 1, 1, 4, 4, 1, 1, 1, 1, 4, 1, 4, 1, 1, 1, 1, 4, 1, 4, 1, 1, 1, 1, 4, 4, 4, 4, 4, 1, 4, 1, 4, 4, 4, 4, 4, 4, 1, 4, 1, 4, 4, 4, 4, 4, 1, 1, 4, 1, 4, 1, 1, 1, 1, 1, 1, 1, 1, 4, 1, 4, 1, 1, 4, 4, 4, 4, 4, 1, 4, 1, 4, 4, 4, 4, 4, 4, 1, 4, 1, 4, 4, 4, 4, 4, 1, 1, 1, 1, 1, 1, 1, 1, 4, 4, 1, 1, 1, 1, 1, 1, 1, 1, 4, 4, 1, 4, 4, 1, 4, 4, 4, 1, 4, 4, 1, 4, 4, 4, 1, 4, 4, 1, 4, 4, 1, 1, 4, 1, 1, 1, 4, 1, 4, 4, 1, 4, 1, 1, 1, 4, 1, 1, 4, 4, 4, 1, 4, 1, 4, 1, 1, 1, 1, 1, 1, 1, 1, 4, 1, 4, 1, 4, 4, 4, 1, 1, 1, 1, 4, 1, 4, 4, 4, 4, 4, 4, 1, 4, 1, 1, 1, 1, 4, 4, 1, 4, 4, 4, 4, 1, 4, 4, 4, 4, 4, 4, 1, 4, 4, 4, 4, 1, 4, 4, 1, 1, 1, 1, 1, 1, 1, 1, 1, 1, 1, 1, 1, 1, 1, 1, 1, 1, 4, 4, 4, 4, 4, 4, 4, 4, 4, 4, 4, 4, 4, 4, 4, 4, 4, 4, 4, 4, 4],
         "height":23,
         "id":1,
         "name":"Tile Layer 1",
         "opacity":1,
         "type":"tilelayer",
         "visible":true,
         "width":20,
         "x":0,
         "y":0
        }, 
        {
         "data":[0, 0, 0, 0, 0, 0, 0, 0, 0, 0, 0, 0, 0, 0, 0, 0, 0, 0, 0, 0, 0, 2, 2, 2, 2, 2, 2, 2, 2, 0, 0, 2, 2, 2, 2, 2, 2, 2, 2, 0, 0, 5, 0, 0, 2, 0, 0, 0, 2, 0, 0, 2, 0, 0, 0, 2, 0, 0, 5, 0, 0, 2, 0, 0, 2, 0, 0, 0, 2, 0, 0, 2, 0, 0, 0, 2, 0, 0, 2, 0, 0, 2, 2, 2, 2, 2, 2, 2, 2, 2, 2, 2, 2, 2, 2, 2, 2, 2, 2, 0, 0, 2, 0, 0, 2, 0, 2, 0, 0, 0, 0, 0, 0, 2, 0, 2, 0, 0, 2, 0, 0, 2, 2, 2, 2, 0, 2, 2, 2, 0, 0, 2, 2, 2, 0, 2, 2, 2, 2, 0, 0, 0, 0, 0, 2, 0, 0, 0, 2, 0, 0, 2, 0, 0, 0, 2, 0, 0, 0, 0, 0, 0, 0, 0, 2, 0, 2, 2, 2, 2, 2, 2, 2, 2, 0, 2, 0, 0, 0, 0, 0, 0, 0, 0, 2, 0, 2, 0, 0, 0, 0, 0, 0, 2, 0, 2, 0, 0, 0, 0, 0, 0, 0, 0, 2, 2, 2, 0, 0, 0, 0, 0, 0, 2, 2, 2, 0, 0, 0, 0, 0, 0, 0, 0, 2, 0, 2, 0, 0, 0, 0, 0, 0, 2, 0, 2, 0, 0, 0, 0, 0, 0, 0, 0, 2, 0, 2, 0, 0, 0, 0, 0, 0, 2, 0, 2, 0, 0, 0, 0, 0, 0, 0, 0, 2, 0, 2, 2, 2, 2, 2, 2, 2, 2, 0, 2, 0, 0, 0, 0, 0, 0, 0, 0, 2, 0, 2, 0, 0, 0, 0, 0, 0, 2, 0, 2, 0, 0, 0, 0, 0, 2, 2, 2, 2, 2, 2, 2, 2, 0, 0, 2, 2, 2, 2, 2, 2, 2, 2, 0, 0, 2, 0, 0, 2, 0, 0, 0, 2, 0, 0, 2, 0, 0, 0, 2, 0, 0, 2, 0, 0, 2, 5, 0, 2, 2, 2, 0, 2, 0, 0, 2, 0, 2, 2, 2, 0, 5, 2, 0, 0, 0, 2, 0, 2, 0, 2, 2, 2, 2, 2, 2, 2, 2, 0, 2, 0, 2, 0, 0, 0, 2, 2, 2, 2, 0, 2, 0, 0, 0, 0, 0, 0, 2, 0, 2, 2, 2, 2, 0, 0, 2, 0, 0, 0, 0, 2, 0, 0, 0, 0, 0, 0, 2, 0, 0, 0, 0, 2, 0, 0, 2, 2, 2, 2, 2, 2, 2, 2, 2, 2, 2, 2, 2, 2, 2, 2, 2, 2, 0, 0, 0, 0, 0, 0, 0, 0, 0, 0, 0, 0, 0, 0, 0, 0, 0, 0, 0, 0, 0],
         "height":23,
         "id":2,
         "name":"Tile Layer 2",
         "opacity":1,
         "type":"tilelayer",
         "visible":true,
         "width":20,
         "x":0,
         "y":0
        }],
 "nextlayerid":3,
 "nextobjectid":1,
 "orientation":"orthogonal",
 "renderorder":"right-down",
 "tiledversion":"1.7.2",
 "tileheight":24,
 "tilesets":[
        {
         "columns":5,
         "firstgid":1,
         "image":"..\/..\/dist\/assets\/tileset.png",
         "imageheight":24,
         "imagewidth":120,
         "margin":0,
         "name":"blocks",
         "spacing":0,
         "tilecount":5,
         "tileheight":24,
         "tiles":[
                {
                 "id":0,
                 "properties":[
                        {
                         "name":"collides",
                         "type":"bool",
                         "value":false
                        }]
                }, 
                {
                 "id":1,
                 "properties":[
                        {
                         "name":"collides",
                         "type":"bool",
                         "value":false
                        }]
                }, 
                {
                 "id":2,
                 "properties":[
                        {
                         "name":"collides",
                         "type":"bool",
                         "value":false
                        }]
                }, 
                {
                 "id":3,
                 "properties":[
                        {
                         "name":"collides",
                         "type":"bool",
                         "value":true
                        }]
                }, 
                {
                 "id":4,
                 "properties":[
                        {
                         "name":"collides",
                         "type":"bool",
                         "value":false
                        }]
                }],
         "tilewidth":24
        }],
 "tilewidth":24,
 "type":"map",
 "version":"1.6",
 "width":20
}